[{
    "name":"Статья 2. Управление транспортным средством (ДК)",
    "item":[{
        "amount":"100000",
        "reason":"2.1.1 ДК",
        "text":"2.1.1 Управление транспортным средством по полосе, предназначенной для встречного движения. Исключение: Объезд препятствия, предотвращение ДТП или если это разрешено разметкой/знаками."
      },{
        "amount":"100000",
        "reason":"2.1.2 ДК",
        "text":"2.1.2 Движение по железнодорожным путям."
      },{
        "amount":"125000",
        "reason":"2.1.3 ДК",
        "text":"2.1.3 Движение транспортных средств по обочинам, тротуарам, пешеходным и велосипедным дорожкам."
      },{
        "amount":"120000",
        "reason":"2.2.1 ДК",
        "text":"2.2.1 Управление транспортным средством в состоянии алкогольного, \"укроп\"тического или иного токсического опьянения."
      },{
        "amount":"100000",
        "reason":"2.2.2 ДК",
        "text":"2.2.2 Использование мобильного телефона водителем во время движения."
      },{
        "amount":"200000",
        "reason":"2.2.3 ДК",
        "text":"2.2.3 Управление транспортным средством без установленных номерных знаков."
      },{
        "amount":"50000",
        "reason":"2.2.4 ДК",
        "text":"2.2.4 Управление транспортным средством с выключенными фарами в темное время суток (с 21:00 до 07:00)."
      },{
        "amount":"150000",
        "reason":"2.3.1 ДК",
        "text":"2.3.1 Превышение установленного скоростного режима. Лимиты скорости: в населенных пунктах — 100 км/ч; вне населенных пунктов — 160 км/ч; на автомагистралях — 180 км/ч."
      },{
        "amount":"200000",
        "reason":"2.4.2 ДК",
        "text":"2.4.2 К спецтранспорту относятся служебные автомобили: Министерства Юстиции, Офиса Генерального прокурора, Медицинских центров, Пожарного департамента, Правительства, а также спецтехника Министерства Обороны."
      }]
  },{
    "name":"Статья 3. Пешеходы и парковка (ДК)",
    "item":[{
        "amount":"200000",
        "reason":"3.1.2 ДК",
        "text":"3.1.2 Переход дороги в неположенном месте или передвижение по проезжей части при наличии тротуара."
      }]
  },{
    "name":"Статья 4. Происшествия и затруднение движения (ДК)",
    "item":[{
        "amount":"100000",
        "reason":"4.1.1 ДК",
        "text":"4.1.1 Умышленное создание помех (затруднение движения) на проезжей части."
      },{
        "amount":"100000",
        "reason":"4.1.2 ДК",
        "text":"4.1.2 Создание помех движению, повлекшее за собой ДТП."
      }]
  },{
    "name":"ГЛАВА IV. ПРАВОНАРУШЕНИЯ ПРОТИВ ЛИЧНОСТИ (АК)",
    "item":[{
        "amount":"1000000",
        "reason":"4.1 АК",
        "text":"Статья 4.1. Оскорбление, то есть унижение чести и достоинства другого лица, выраженное в неприличной или иной противоречащей общепринятым нормам морали форме."
      },{
        "amount":"1000000",
        "reason":"4.2 АК",
        "text":"Статья 4.2. Нарушение прав, свобод и законных интересов человека и гражданина в зависимости от его пола, расы, цвета кожи, национальности, языка, происхождения, имущественного, семейного, социального и должностного положения, возраста, места жительства, отношения к религии."
      },{
        "amount":"1000000",
        "reason":"4.3 АК",
        "text":"Статья 4.3. Воспрепятствование в какой бы то ни было форме законной деятельности медицинского работника по оказанию медицинской помощи."
      }]
  },{
    "name":"ГЛАВА V. ПРАВОНАРУШЕНИЯ ПРОТИВ ОБЩЕСТВЕННОГО ПОРЯДКА (АК)",
    "item":[{
        "amount":"500000",
        "reason":"5.1 АК",
        "text":"Статья 5.1. Нарушение общественного порядка, выражающее явное неуважение к обществу, сопровождающееся нецензурной бранью в общественных местах, оскорбительным приставанием к гражданам, а равно уничтожением или повреждением чужого имущества."
      },{
        "amount":"500000",
        "reason":"5.2 АК",
        "text":"Статья 5.2. Ношение маски, балаклавы или иных средств, скрывающих лицо, в общественных местах. Исключение: медицинские маски, сотрудники спецподразделений МО/МЮ при исполнении."
      },{
        "amount":"1000000",
        "reason":"5.3 АК",
        "text":"Статья 5.3. Употребление табачных изделий, алкогольной продукции, укропотических или психотропных веществ в государственных учреждениях и местах массового скопления людей."
      },{
        "amount":"1000000",
        "reason":"5.3.1 АК",
        "text":"Статья 5.3. Заведомо ложный вызов пожарной охраны, полиции, скорой медицинской помощи или иных специализированных служб."
      },{
        "amount":"1000000",
        "reason":"5.4 АК",
        "text":"Статья 5.4. Нанесение побоев или совершение иных насильственных действий, причинивших физическую боль, но не повлекших последствий, указанных в Уголовном кодексе."
      },{
        "amount":"1000000",
        "reason":"5.5 АК",
        "text":"Статья 5.5. Воспрепятствование законной деятельности сотрудников правоохранительных органов, военнослужащих при исполнении, сотрудников экстренных служб, а также первых лиц штата, если это деяние не содержит признаков уголовного преступления."
      },{
        "amount":"1000000",
        "reason":"5.6 АК",
        "text":"Статья 5.6. Неповиновение законному распоряжению или требованию сотрудника правоохранительных органов, сотрудника Офиса Генерального прокурора или военнослужащего при исполнении ими служебных обязанностей."
      }]
  },{
    "name":"ГЛАВА VI. ПРАВОНАРУШЕНИЯ В СФЕРЕ ТРУДА И УПРАВЛЕНИЯ (АК)",
    "item":[{
        "amount":"3000000",
        "reason":"6.1 АК",
        "text":"Статья 6.1. Отказ руководства организации от выплаты компенсаций за сверхурочную работу, принуждение к труду."
      },{
        "amount":"3000000",
        "reason":"6.2 АК",
        "text":"Статья 6.2. Несвоевременная проверка заявлений, отчётов и обращений граждан со стороны руководства государственной структуры. Исключение: сложные делопроизводства и незавершенные обращения."
      },{
        "amount":"3000000",
        "reason":"6.3 АК",
        "text":"Статья 6.3. Нарушение правил формирования рабочего графика, требование работы вне рабочего времени против желания работника (при отсутствии ЧС)."
      },{
        "amount":"2000000",
        "reason":"6.4 АК",
        "text":"Статья 6.4. Игнорирование указов Губернатора или постановлений Федерального Правительства касательно установки заработных плат и премирования сотрудников."
      },{
        "amount":"3000000",
        "reason":"6.5 АК",
        "text":"Статья 6.5. Иные нарушения прав работников, предусмотренные Трудовым кодексом или уставами организаций."
      },{
        "amount":"2000000",
        "reason":"6.6 АК",
        "text":"Статья 6.6. Действия, выражающие явное неуважение к суду или судье, нарушение порядка в судебном заседании, неподчинение распоряжениям судьи или судебного пристава."
      }]
  },{
    "name":"##updated_at",
    "updated_at":1779046774
  }]
